mmbse_client/__init__.py
mmbse_client/mmbse.py
mmbse_client-1.1.0.dist-info/METADATA
mmbse_client-1.1.0.dist-info/WHEEL
mmbse_client-1.1.0.dist-info/RECORD
